cesarview/__init__.pyc
cesarview/base/__init__.pyc
cesarview/base/__init__.pyi
cesarview/base/cs_base_alignment.pyc
cesarview/base/cs_base_alignment.pyi
cesarview/base/cs_base_box.pyc
cesarview/base/cs_base_box.pyi
cesarview/base/cs_base_btn.pyc
cesarview/base/cs_base_btn.pyi
cesarview/base/cs_base_dialog.pyc
cesarview/base/cs_base_dialog.pyi
cesarview/base/cs_base_widget.pyc
cesarview/base/cs_base_widget.pyi
cesarview/helper/__init__.pyc
cesarview/helper/__init__.pyi
cesarview/helper/cs_colors.pyc
cesarview/helper/cs_colors.pyi
cesarview/resources/svg/check.svg
cesarview/resources/svg/edit.svg
cesarview/resources/svg/email.svg
cesarview/resources/svg/search.svg
cesarview/resources/svg/star.svg
cesarview/resources/svg/trash.svg
cesarview/theme/__init__.pyc
cesarview/theme/__init__.pyi
cesarview/theme/cs_theme_item.pyc
cesarview/theme/cs_theme_item.pyi
cesarview/theme/cs_themes.pyc
cesarview/theme/cs_themes.pyi
cesarview/theme/default_config.pyc
cesarview/theme/default_config.pyi
cesarview/widgets/__init__.pyc
cesarview/widgets/__init__.pyi
cesarview/widgets/cs_btn.pyc
cesarview/widgets/cs_btn.pyi
cesarview-0.5.3.dist-info/METADATA
cesarview-0.5.3.dist-info/WHEEL
cesarview-0.5.3.dist-info/top_level.txt
cesarview-0.5.3.dist-info/RECORD
